clipboard_mcp/__init__.py
clipboard_mcp/server.py
clipboard_mcp-0.1.3.dist-info/licenses/LICENSE
clipboard_mcp-0.1.3.dist-info/METADATA
clipboard_mcp-0.1.3.dist-info/WHEEL
clipboard_mcp-0.1.3.dist-info/entry_points.txt
clipboard_mcp-0.1.3.dist-info/top_level.txt
clipboard_mcp-0.1.3.dist-info/RECORD
