Metadata-Version: 2.4
Name: clipboard-mcp
Version: 0.1.3
Summary: MCP Server for system clipboard integration
Author-email: Gabi Teodoru <gabiteodoru@gmail.com>
License: MIT
Project-URL: Homepage, https://github.com/gabiteodoru/clipboard-mcp
Project-URL: Bug Tracker, https://github.com/gabiteodoru/clipboard-mcp/issues
Project-URL: Source Code, https://github.com/gabiteodoru/clipboard-mcp
Requires-Python: >=3.8
License-File: LICENSE
Requires-Dist: mcp
Requires-Dist: pyperclip
Dynamic: license-file
